touch_brainf/__init__.py
touch_brainf/__main__.py
touch_brainf/runner.py
touch_brainf/utils.py
touch_brainf/data/version.txt
touch_brainf/errors/__init__.py
touch_brainf/errors/pointer_not_in_range_error.py
touch_brainf-25.3.20.dist-info/LICENSE.txt
touch_brainf-25.3.20.dist-info/METADATA
touch_brainf-25.3.20.dist-info/WHEEL
touch_brainf-25.3.20.dist-info/entry_points.txt
touch_brainf-25.3.20.dist-info/top_level.txt
touch_brainf-25.3.20.dist-info/RECORD
