Metadata-Version: 2.1
Name: touch_brainf
Version: 25.3.20
Summary: BrainF interpreter Python package
Home-page: https://github.com/Touchcreator/touch-brainf
Author: Touchcreator (Tochukwu Okolo)
Author-email: tochukwu.m.okolo@gmail.com
License: MIT
Keywords: brainf,branflakes,brainfuck,python,touchcreator
Classifier: License :: OSI Approved :: MIT License
Classifier: Programming Language :: Python :: 3
Classifier: Programming Language :: Python :: 3.12
Classifier: Programming Language :: Python :: Implementation
Classifier: Programming Language :: Python :: Implementation :: CPython
License-File: LICENSE.txt
